{"day":"2026-07-23","forecast_for":"2026-07-24","observed":{"updated":"2026-07-23T06:39Z","stations":{"41001":{"name":"E Hatteras","upstream":true,"wvht_ft":5.2,"dpd_s":7,"mwd_deg":247,"wspd_kt":16,"wdir_deg":190,"wtmp_f":81,"obs_time":"2026-07-23T05:50Z","model_wvht_ft":5.9},"41002":{"name":"S Hatteras","upstream":true,"wvht_ft":3.3,"dpd_s":8,"mwd_deg":144,"wspd_kt":10,"wdir_deg":170,"wtmp_f":86,"obs_time":"2026-07-23T05:50Z","model_wvht_ft":3.4},"41025":{"name":"Diamond Shoals","wvht_ft":5.6,"dpd_s":5,"mwd_deg":204,"wspd_kt":21,"wdir_deg":220,"wtmp_f":84,"obs_time":"2026-07-23T05:50Z","model_wvht_ft":5.9},"44100":{"name":"Duck (waverider)","wvht_ft":3.6,"dpd_s":6,"mwd_deg":147,"wspd_kt":null,"wdir_deg":null,"wtmp_f":78,"obs_time":"2026-07-23T06:00Z","model_wvht_ft":3.3}}},"observed_hourly":{"41001":[{"t":"2026-07-23T06:10Z","wvht_ft":null,"dpd_s":null,"mwd_deg":null,"wspd_kt":16,"wdir_deg":190},{"t":"2026-07-23T05:50Z","wvht_ft":5.2,"dpd_s":7,"mwd_deg":247,"wspd_kt":16,"wdir_deg":190},{"t":"2026-07-23T04:50Z","wvht_ft":5.6,"dpd_s":7,"mwd_deg":242,"wspd_kt":16,"wdir_deg":190},{"t":"2026-07-23T03:50Z","wvht_ft":5.2,"dpd_s":7,"mwd_deg":232,"wspd_kt":14,"wdir_deg":180},{"t":"2026-07-23T02:50Z","wvht_ft":5.2,"dpd_s":7,"mwd_deg":253,"wspd_kt":14,"wdir_deg":190},{"t":"2026-07-23T01:50Z","wvht_ft":5.9,"dpd_s":7,"mwd_deg":240,"wspd_kt":14,"wdir_deg":200},{"t":"2026-07-23T00:50Z","wvht_ft":5.6,"dpd_s":7,"mwd_deg":251,"wspd_kt":14,"wdir_deg":190},{"t":"2026-07-22T23:50Z","wvht_ft":5.9,"dpd_s":8,"mwd_deg":238,"wspd_kt":14,"wdir_deg":200},{"t":"2026-07-22T22:50Z","wvht_ft":5.9,"dpd_s":8,"mwd_deg":184,"wspd_kt":16,"wdir_deg":190},{"t":"2026-07-22T21:50Z","wvht_ft":7.2,"dpd_s":7,"mwd_deg":229,"wspd_kt":16,"wdir_deg":190},{"t":"2026-07-22T20:50Z","wvht_ft":6.6,"dpd_s":8,"mwd_deg":227,"wspd_kt":16,"wdir_deg":190},{"t":"2026-07-22T19:50Z","wvht_ft":6.2,"dpd_s":8,"mwd_deg":241,"wspd_kt":16,"wdir_deg":200},{"t":"2026-07-22T18:50Z","wvht_ft":5.9,"dpd_s":7,"mwd_deg":227,"wspd_kt":16,"wdir_deg":200},{"t":"2026-07-22T17:50Z","wvht_ft":5.9,"dpd_s":8,"mwd_deg":229,"wspd_kt":16,"wdir_deg":200},{"t":"2026-07-22T16:50Z","wvht_ft":6.2,"dpd_s":7,"mwd_deg":229,"wspd_kt":16,"wdir_deg":200},{"t":"2026-07-22T15:50Z","wvht_ft":5.9,"dpd_s":7,"mwd_deg":226,"wspd_kt":17,"wdir_deg":200},{"t":"2026-07-22T14:50Z","wvht_ft":5.9,"dpd_s":7,"mwd_deg":229,"wspd_kt":17,"wdir_deg":200},{"t":"2026-07-22T13:50Z","wvht_ft":5.6,"dpd_s":7,"mwd_deg":223,"wspd_kt":16,"wdir_deg":200},{"t":"2026-07-22T12:50Z","wvht_ft":6.2,"dpd_s":7,"mwd_deg":239,"wspd_kt":16,"wdir_deg":200},{"t":"2026-07-22T11:50Z","wvht_ft":5.6,"dpd_s":7,"mwd_deg":235,"wspd_kt":17,"wdir_deg":200},{"t":"2026-07-22T10:50Z","wvht_ft":5.6,"dpd_s":7,"mwd_deg":217,"wspd_kt":16,"wdir_deg":200},{"t":"2026-07-22T09:50Z","wvht_ft":5.9,"dpd_s":7,"mwd_deg":232,"wspd_kt":17,"wdir_deg":200},{"t":"2026-07-22T08:50Z","wvht_ft":5.9,"dpd_s":7,"mwd_deg":216,"wspd_kt":16,"wdir_deg":200},{"t":"2026-07-22T07:50Z","wvht_ft":6.2,"dpd_s":6,"mwd_deg":223,"wspd_kt":17,"wdir_deg":200},{"t":"2026-07-22T06:50Z","wvht_ft":5.6,"dpd_s":6,"mwd_deg":221,"wspd_kt":19,"wdir_deg":190}],"41002":[{"t":"2026-07-23T06:10Z","wvht_ft":null,"dpd_s":null,"mwd_deg":null,"wspd_kt":10,"wdir_deg":170},{"t":"2026-07-23T05:50Z","wvht_ft":3.3,"dpd_s":8,"mwd_deg":144,"wspd_kt":10,"wdir_deg":180},{"t":"2026-07-23T04:50Z","wvht_ft":3.3,"dpd_s":6,"mwd_deg":273,"wspd_kt":10,"wdir_deg":170},{"t":"2026-07-23T03:50Z","wvht_ft":3.3,"dpd_s":8,"mwd_deg":127,"wspd_kt":12,"wdir_deg":160},{"t":"2026-07-23T02:50Z","wvht_ft":3.3,"dpd_s":6,"mwd_deg":229,"wspd_kt":12,"wdir_deg":160},{"t":"2026-07-23T01:50Z","wvht_ft":3.3,"dpd_s":6,"mwd_deg":259,"wspd_kt":10,"wdir_deg":160},{"t":"2026-07-23T00:50Z","wvht_ft":3.3,"dpd_s":7,"mwd_deg":197,"wspd_kt":10,"wdir_deg":170},{"t":"2026-07-22T23:50Z","wvht_ft":3.3,"dpd_s":8,"mwd_deg":131,"wspd_kt":10,"wdir_deg":170},{"t":"2026-07-22T22:50Z","wvht_ft":3.3,"dpd_s":8,"mwd_deg":136,"wspd_kt":10,"wdir_deg":180},{"t":"2026-07-22T21:50Z","wvht_ft":3.3,"dpd_s":8,"mwd_deg":132,"wspd_kt":6,"wdir_deg":190},{"t":"2026-07-22T20:50Z","wvht_ft":3.3,"dpd_s":7,"mwd_deg":129,"wspd_kt":8,"wdir_deg":210},{"t":"2026-07-22T19:50Z","wvht_ft":3.6,"dpd_s":6,"mwd_deg":212,"wspd_kt":14,"wdir_deg":190},{"t":"2026-07-22T18:50Z","wvht_ft":3.6,"dpd_s":null,"mwd_deg":222,"wspd_kt":10,"wdir_deg":180},{"t":"2026-07-22T17:50Z","wvht_ft":3.6,"dpd_s":8,"mwd_deg":126,"wspd_kt":10,"wdir_deg":190},{"t":"2026-07-22T16:50Z","wvht_ft":3.6,"dpd_s":8,"mwd_deg":132,"wspd_kt":12,"wdir_deg":200},{"t":"2026-07-22T15:50Z","wvht_ft":3.3,"dpd_s":8,"mwd_deg":156,"wspd_kt":12,"wdir_deg":190},{"t":"2026-07-22T14:50Z","wvht_ft":3.6,"dpd_s":5,"mwd_deg":210,"wspd_kt":12,"wdir_deg":190},{"t":"2026-07-22T13:50Z","wvht_ft":3.3,"dpd_s":6,"mwd_deg":185,"wspd_kt":14,"wdir_deg":190},{"t":"2026-07-22T12:50Z","wvht_ft":3.6,"dpd_s":8,"mwd_deg":138,"wspd_kt":12,"wdir_deg":190},{"t":"2026-07-22T11:50Z","wvht_ft":3.6,"dpd_s":8,"mwd_deg":134,"wspd_kt":14,"wdir_deg":190},{"t":"2026-07-22T10:50Z","wvht_ft":3.6,"dpd_s":6,"mwd_deg":206,"wspd_kt":14,"wdir_deg":180},{"t":"2026-07-22T09:50Z","wvht_ft":3.9,"dpd_s":8,"mwd_deg":135,"wspd_kt":14,"wdir_deg":190},{"t":"2026-07-22T08:50Z","wvht_ft":3.9,"dpd_s":8,"mwd_deg":142,"wspd_kt":14,"wdir_deg":180},{"t":"2026-07-22T07:50Z","wvht_ft":3.9,"dpd_s":null,"mwd_deg":180,"wspd_kt":14,"wdir_deg":180},{"t":"2026-07-22T06:50Z","wvht_ft":3.6,"dpd_s":5,"mwd_deg":218,"wspd_kt":16,"wdir_deg":190}],"41025":[{"t":"2026-07-23T06:10Z","wvht_ft":null,"dpd_s":null,"mwd_deg":null,"wspd_kt":21,"wdir_deg":220},{"t":"2026-07-23T05:50Z","wvht_ft":5.6,"dpd_s":5,"mwd_deg":204,"wspd_kt":21,"wdir_deg":220},{"t":"2026-07-23T04:50Z","wvht_ft":5.2,"dpd_s":6,"mwd_deg":217,"wspd_kt":23,"wdir_deg":220},{"t":"2026-07-23T03:50Z","wvht_ft":5.6,"dpd_s":6,"mwd_deg":216,"wspd_kt":23,"wdir_deg":220},{"t":"2026-07-23T02:50Z","wvht_ft":5.6,"dpd_s":5,"mwd_deg":201,"wspd_kt":23,"wdir_deg":200},{"t":"2026-07-23T01:50Z","wvht_ft":5.6,"dpd_s":null,"mwd_deg":206,"wspd_kt":null,"wdir_deg":null},{"t":"2026-07-23T00:50Z","wvht_ft":5.6,"dpd_s":null,"mwd_deg":215,"wspd_kt":null,"wdir_deg":null},{"t":"2026-07-22T23:50Z","wvht_ft":5.6,"dpd_s":5,"mwd_deg":209,"wspd_kt":23,"wdir_deg":210},{"t":"2026-07-22T22:50Z","wvht_ft":5.6,"dpd_s":6,"mwd_deg":211,"wspd_kt":23,"wdir_deg":210},{"t":"2026-07-22T21:50Z","wvht_ft":5.9,"dpd_s":6,"mwd_deg":221,"wspd_kt":23,"wdir_deg":210},{"t":"2026-07-22T20:50Z","wvht_ft":5.9,"dpd_s":5,"mwd_deg":223,"wspd_kt":23,"wdir_deg":210},{"t":"2026-07-22T19:50Z","wvht_ft":6.2,"dpd_s":7,"mwd_deg":218,"wspd_kt":23,"wdir_deg":220},{"t":"2026-07-22T18:50Z","wvht_ft":6.6,"dpd_s":6,"mwd_deg":217,"wspd_kt":null,"wdir_deg":null},{"t":"2026-07-22T17:50Z","wvht_ft":6.6,"dpd_s":7,"mwd_deg":212,"wspd_kt":23,"wdir_deg":220},{"t":"2026-07-22T16:50Z","wvht_ft":6.2,"dpd_s":6,"mwd_deg":218,"wspd_kt":23,"wdir_deg":220},{"t":"2026-07-22T15:50Z","wvht_ft":6.2,"dpd_s":7,"mwd_deg":209,"wspd_kt":25,"wdir_deg":220},{"t":"2026-07-22T14:50Z","wvht_ft":6.2,"dpd_s":7,"mwd_deg":210,"wspd_kt":25,"wdir_deg":220},{"t":"2026-07-22T13:50Z","wvht_ft":5.9,"dpd_s":6,"mwd_deg":216,"wspd_kt":25,"wdir_deg":220},{"t":"2026-07-22T12:50Z","wvht_ft":6.2,"dpd_s":6,"mwd_deg":213,"wspd_kt":25,"wdir_deg":220},{"t":"2026-07-22T11:50Z","wvht_ft":6.6,"dpd_s":7,"mwd_deg":213,"wspd_kt":25,"wdir_deg":220},{"t":"2026-07-22T10:50Z","wvht_ft":6.9,"dpd_s":6,"mwd_deg":218,"wspd_kt":25,"wdir_deg":220},{"t":"2026-07-22T09:50Z","wvht_ft":7.2,"dpd_s":6,"mwd_deg":210,"wspd_kt":25,"wdir_deg":220},{"t":"2026-07-22T08:50Z","wvht_ft":7.9,"dpd_s":7,"mwd_deg":216,"wspd_kt":27,"wdir_deg":220},{"t":"2026-07-22T07:50Z","wvht_ft":8.2,"dpd_s":6,"mwd_deg":211,"wspd_kt":29,"wdir_deg":220},{"t":"2026-07-22T06:50Z","wvht_ft":7.9,"dpd_s":6,"mwd_deg":216,"wspd_kt":27,"wdir_deg":220}],"44100":[{"t":"2026-07-23T06:00Z","wvht_ft":3.6,"dpd_s":6,"mwd_deg":147,"wspd_kt":null,"wdir_deg":null},{"t":"2026-07-23T05:30Z","wvht_ft":3.6,"dpd_s":7,"mwd_deg":142,"wspd_kt":null,"wdir_deg":null},{"t":"2026-07-23T04:30Z","wvht_ft":3.9,"dpd_s":6,"mwd_deg":147,"wspd_kt":null,"wdir_deg":null},{"t":"2026-07-23T03:30Z","wvht_ft":3.9,"dpd_s":5,"mwd_deg":159,"wspd_kt":null,"wdir_deg":null},{"t":"2026-07-23T02:30Z","wvht_ft":3.9,"dpd_s":6,"mwd_deg":149,"wspd_kt":null,"wdir_deg":null},{"t":"2026-07-23T01:30Z","wvht_ft":3.6,"dpd_s":8,"mwd_deg":135,"wspd_kt":null,"wdir_deg":null},{"t":"2026-07-23T00:30Z","wvht_ft":3.6,"dpd_s":4,"mwd_deg":153,"wspd_kt":null,"wdir_deg":null},{"t":"2026-07-22T23:30Z","wvht_ft":3.6,"dpd_s":5,"mwd_deg":152,"wspd_kt":null,"wdir_deg":null},{"t":"2026-07-22T22:30Z","wvht_ft":3.3,"dpd_s":6,"mwd_deg":151,"wspd_kt":null,"wdir_deg":null},{"t":"2026-07-22T21:30Z","wvht_ft":3.3,"dpd_s":7,"mwd_deg":147,"wspd_kt":null,"wdir_deg":null},{"t":"2026-07-22T20:30Z","wvht_ft":3.3,"dpd_s":6,"mwd_deg":147,"wspd_kt":null,"wdir_deg":null},{"t":"2026-07-22T19:30Z","wvht_ft":3.6,"dpd_s":5,"mwd_deg":155,"wspd_kt":null,"wdir_deg":null},{"t":"2026-07-22T18:30Z","wvht_ft":3.6,"dpd_s":5,"mwd_deg":162,"wspd_kt":null,"wdir_deg":null},{"t":"2026-07-22T17:30Z","wvht_ft":3.6,"dpd_s":6,"mwd_deg":154,"wspd_kt":null,"wdir_deg":null},{"t":"2026-07-22T16:30Z","wvht_ft":3.9,"dpd_s":5,"mwd_deg":163,"wspd_kt":null,"wdir_deg":null},{"t":"2026-07-22T15:30Z","wvht_ft":3.6,"dpd_s":5,"mwd_deg":160,"wspd_kt":null,"wdir_deg":null},{"t":"2026-07-22T14:30Z","wvht_ft":3.6,"dpd_s":5,"mwd_deg":160,"wspd_kt":null,"wdir_deg":null},{"t":"2026-07-22T13:30Z","wvht_ft":3.6,"dpd_s":5,"mwd_deg":155,"wspd_kt":null,"wdir_deg":null},{"t":"2026-07-22T12:30Z","wvht_ft":3.9,"dpd_s":7,"mwd_deg":144,"wspd_kt":null,"wdir_deg":null},{"t":"2026-07-22T11:30Z","wvht_ft":3.6,"dpd_s":8,"mwd_deg":142,"wspd_kt":null,"wdir_deg":null},{"t":"2026-07-22T10:30Z","wvht_ft":3.6,"dpd_s":7,"mwd_deg":149,"wspd_kt":null,"wdir_deg":null},{"t":"2026-07-22T09:30Z","wvht_ft":3.9,"dpd_s":6,"mwd_deg":145,"wspd_kt":null,"wdir_deg":null},{"t":"2026-07-22T08:30Z","wvht_ft":4.3,"dpd_s":7,"mwd_deg":146,"wspd_kt":null,"wdir_deg":null},{"t":"2026-07-22T07:30Z","wvht_ft":4.6,"dpd_s":4,"mwd_deg":164,"wspd_kt":null,"wdir_deg":null}]},"zones":{"points":[[36.36,-75.77],[36.16,-75.72],[36.02,-75.64],[35.9,-75.56],[35.82,-75.52],[35.7,-75.45],[35.58,-75.43],[35.34,-75.46],[35.24,-75.48],[35.17,-75.6],[35.16,-75.69],[35.06,-75.95]],"forecast":[{"marine":{"time":["2026-07-24T00:00","2026-07-24T01:00","2026-07-24T02:00","2026-07-24T03:00","2026-07-24T04:00","2026-07-24T05:00","2026-07-24T06:00","2026-07-24T07:00","2026-07-24T08:00","2026-07-24T09:00","2026-07-24T10:00","2026-07-24T11:00","2026-07-24T12:00","2026-07-24T13:00","2026-07-24T14:00","2026-07-24T15:00","2026-07-24T16:00","2026-07-24T17:00","2026-07-24T18:00","2026-07-24T19:00","2026-07-24T20:00","2026-07-24T21:00","2026-07-24T22:00","2026-07-24T23:00"],"wave_height":[0.52,0.52,0.52,0.52,0.52,0.52,0.54,0.56,0.58,0.6,0.6,0.62,0.6,0.6,0.58,0.58,0.58,0.58,0.58,0.58,0.58,0.58,0.56,0.56],"wave_period":[4.1,4.1,4.15,4.2,4.25,4.25,4.2,4.15,4.1,4.1,4.1,4.1,4.15,4.25,4.3,4.35,4.4,4.4,4.4,4.4,4.4,4.45,4.55,4.65],"wave_direction":[72,72,73,73,74,74,73,71,70,69,68,67,68,69,70,70,70,70,70,71,71,72,73,74],"swell_wave_height":[0.26,0.26,0.26,0.26,0.26,0.26,0.26,0.26,0.26,0.26,0.26,0.26,0.28,0.32,0.34,0.34,0.34,0.34,0.32,0.32,0.3,0.34,0.36,0.4],"swell_wave_period":[3,3.2,3.5,4.1,4.8,5.4,5.7,5.8,5.85,5.9,5.95,5.75,5.2,4.45,3.9,3.7,3.65,3.7,3.85,4.05,4.15,4,3.8,3.65],"swell_wave_direction":[29,32,34,63,92,121,121,122,122,122,122,122,97,73,48,54,60,66,66,66,66,64,62,60]},"wind":{"time":["2026-07-24T00:00","2026-07-24T01:00","2026-07-24T02:00","2026-07-24T03:00","2026-07-24T04:00","2026-07-24T05:00","2026-07-24T06:00","2026-07-24T07:00","2026-07-24T08:00","2026-07-24T09:00","2026-07-24T10:00","2026-07-24T11:00","2026-07-24T12:00","2026-07-24T13:00","2026-07-24T14:00","2026-07-24T15:00","2026-07-24T16:00","2026-07-24T17:00","2026-07-24T18:00","2026-07-24T19:00","2026-07-24T20:00","2026-07-24T21:00","2026-07-24T22:00","2026-07-24T23:00"],"wind_speed_10m":[4.9,7.3,7.1,10.3,10.3,6.4,6.8,7.8,14.6,28.7,23.4,15.9,15.8,13.5,13,10.6,13,14.1,11.4,9.5,8.3,7,7.1,6.7],"wind_direction_10m":[270,228,188,209,212,215,177,179,123,172,356,335,339,333,330,306,335,337,269,208,45,60,64,68]}},{"marine":{"time":["2026-07-24T00:00","2026-07-24T01:00","2026-07-24T02:00","2026-07-24T03:00","2026-07-24T04:00","2026-07-24T05:00","2026-07-24T06:00","2026-07-24T07:00","2026-07-24T08:00","2026-07-24T09:00","2026-07-24T10:00","2026-07-24T11:00","2026-07-24T12:00","2026-07-24T13:00","2026-07-24T14:00","2026-07-24T15:00","2026-07-24T16:00","2026-07-24T17:00","2026-07-24T18:00","2026-07-24T19:00","2026-07-24T20:00","2026-07-24T21:00","2026-07-24T22:00","2026-07-24T23:00"],"wave_height":[0.6,0.6,0.6,0.6,0.6,0.6,0.62,0.64,0.66,0.68,0.68,0.7,0.68,0.68,0.66,0.66,0.66,0.66,0.68,0.68,0.7,0.68,0.64,0.62],"wave_period":[4,4,4.05,4.1,4.15,4.2,4.15,4.1,4.05,4.05,4.1,4.15,4.2,4.3,4.35,4.35,4.3,4.3,4.3,4.3,4.3,4.4,4.5,4.6],"wave_direction":[63,64,65,66,67,68,66,64,62,62,63,63,64,66,67,66,64,63,63,63,63,65,67,69],"swell_wave_height":[0.18,0.18,0.2,0.22,0.24,0.26,0.26,0.28,0.28,0.28,0.28,0.28,0.3,0.3,0.32,0.3,0.3,0.28,0.24,0.22,0.18,0.26,0.32,0.4],"swell_wave_period":[4.85,4.2,4,4.7,5.85,6.65,6.75,6.55,6.4,6.5,6.6,6.45,5.7,4.7,4.2,4.8,5.9,6.55,6.3,5.65,5.05,4.55,4.1,3.85],"swell_wave_direction":[72,51,31,60,90,119,120,121,122,122,123,123,99,75,51,74,97,120,102,85,67,63,58,54]},"wind":{"time":["2026-07-24T00:00","2026-07-24T01:00","2026-07-24T02:00","2026-07-24T03:00","2026-07-24T04:00","2026-07-24T05:00","2026-07-24T06:00","2026-07-24T07:00","2026-07-24T08:00","2026-07-24T09:00","2026-07-24T10:00","2026-07-24T11:00","2026-07-24T12:00","2026-07-24T13:00","2026-07-24T14:00","2026-07-24T15:00","2026-07-24T16:00","2026-07-24T17:00","2026-07-24T18:00","2026-07-24T19:00","2026-07-24T20:00","2026-07-24T21:00","2026-07-24T22:00","2026-07-24T23:00"],"wind_speed_10m":[2.7,7.1,7.1,7.9,6.9,5,7,9.7,11.2,13.5,8.5,7.6,8.5,9.5,7.8,5.7,6.5,7.8,8.9,9.3,9.7,10.1,9.3,9],"wind_direction_10m":[270,206,201,205,205,208,178,155,157,187,227,276,305,314,316,301,321,337,273,203,43,60,64,68]}},{"marine":{"time":["2026-07-24T00:00","2026-07-24T01:00","2026-07-24T02:00","2026-07-24T03:00","2026-07-24T04:00","2026-07-24T05:00","2026-07-24T06:00","2026-07-24T07:00","2026-07-24T08:00","2026-07-24T09:00","2026-07-24T10:00","2026-07-24T11:00","2026-07-24T12:00","2026-07-24T13:00","2026-07-24T14:00","2026-07-24T15:00","2026-07-24T16:00","2026-07-24T17:00","2026-07-24T18:00","2026-07-24T19:00","2026-07-24T20:00","2026-07-24T21:00","2026-07-24T22:00","2026-07-24T23:00"],"wave_height":[0.66,0.68,0.68,0.68,0.66,0.66,0.68,0.7,0.72,0.74,0.74,0.76,0.74,0.74,0.72,0.74,0.74,0.76,0.76,0.76,0.76,0.74,0.72,0.7],"wave_period":[4.35,4.35,4.4,4.45,4.55,4.6,4.55,4.5,4.45,4.45,4.45,4.5,4.55,4.65,4.7,4.7,4.65,4.6,4.6,4.65,4.7,4.8,4.9,4.95],"wave_direction":[63,65,67,68,69,70,68,66,64,64,65,65,66,66,67,66,65,64,64,64,64,66,67,69],"swell_wave_height":[0.26,0.28,0.3,0.32,0.36,0.38,0.38,0.36,0.36,0.36,0.36,0.36,0.38,0.38,0.4,0.38,0.38,0.36,0.36,0.36,0.36,0.38,0.42,0.44],"swell_wave_period":[6.75,6.15,5.75,5.9,6.25,6.5,6.55,6.5,6.5,6.65,6.85,6.7,5.85,4.65,4.05,4.55,5.6,6.4,6.7,6.7,6.45,5.75,4.75,4],"swell_wave_direction":[89,90,91,102,112,123,123,124,124,124,124,124,96,67,39,66,94,121,120,120,119,95,72,48]},"wind":{"time":["2026-07-24T00:00","2026-07-24T01:00","2026-07-24T02:00","2026-07-24T03:00","2026-07-24T04:00","2026-07-24T05:00","2026-07-24T06:00","2026-07-24T07:00","2026-07-24T08:00","2026-07-24T09:00","2026-07-24T10:00","2026-07-24T11:00","2026-07-24T12:00","2026-07-24T13:00","2026-07-24T14:00","2026-07-24T15:00","2026-07-24T16:00","2026-07-24T17:00","2026-07-24T18:00","2026-07-24T19:00","2026-07-24T20:00","2026-07-24T21:00","2026-07-24T22:00","2026-07-24T23:00"],"wind_speed_10m":[11.2,8.2,7.9,9.5,7.8,8.2,7.8,10.4,14.2,15.1,11.4,6.1,7,5.6,5.7,5.2,3.5,6.1,7,7.6,9,9.8,8.2,7.1],"wind_direction_10m":[187,188,202,211,203,173,183,151,158,148,243,259,268,306,305,318,279,325,265,200,44,59,62,64]}},{"marine":{"time":["2026-07-24T00:00","2026-07-24T01:00","2026-07-24T02:00","2026-07-24T03:00","2026-07-24T04:00","2026-07-24T05:00","2026-07-24T06:00","2026-07-24T07:00","2026-07-24T08:00","2026-07-24T09:00","2026-07-24T10:00","2026-07-24T11:00","2026-07-24T12:00","2026-07-24T13:00","2026-07-24T14:00","2026-07-24T15:00","2026-07-24T16:00","2026-07-24T17:00","2026-07-24T18:00","2026-07-24T19:00","2026-07-24T20:00","2026-07-24T21:00","2026-07-24T22:00","2026-07-24T23:00"],"wave_height":[0.68,0.7,0.7,0.7,0.7,0.7,0.72,0.74,0.76,0.76,0.78,0.78,0.78,0.76,0.76,0.76,0.78,0.78,0.78,0.78,0.78,0.76,0.74,0.72],"wave_period":[4.35,4.35,4.4,4.5,4.6,4.65,4.6,4.5,4.45,4.45,4.5,4.55,4.6,4.7,4.75,4.75,4.7,4.7,4.7,4.7,4.7,4.75,4.85,4.9],"wave_direction":[60,62,64,65,67,68,67,65,64,64,64,64,64,63,63,63,62,62,62,62,62,63,63,64],"swell_wave_height":[0.3,0.34,0.36,0.38,0.4,0.42,0.42,0.4,0.4,0.4,0.4,0.4,0.4,0.42,0.42,0.4,0.36,0.34,0.34,0.34,0.34,0.38,0.44,0.48],"swell_wave_period":[3.75,4.3,4.75,5.15,5.5,5.75,5.9,5.95,6,6.1,6.15,6,5.5,4.8,4.3,4.3,4.5,4.65,4.7,4.75,4.7,4.5,4.25,4.05],"swell_wave_direction":[43,82,120,119,119,118,122,126,130,124,119,113,88,62,37,39,41,43,43,44,44,45,45,46]},"wind":{"time":["2026-07-24T00:00","2026-07-24T01:00","2026-07-24T02:00","2026-07-24T03:00","2026-07-24T04:00","2026-07-24T05:00","2026-07-24T06:00","2026-07-24T07:00","2026-07-24T08:00","2026-07-24T09:00","2026-07-24T10:00","2026-07-24T11:00","2026-07-24T12:00","2026-07-24T13:00","2026-07-24T14:00","2026-07-24T15:00","2026-07-24T16:00","2026-07-24T17:00","2026-07-24T18:00","2026-07-24T19:00","2026-07-24T20:00","2026-07-24T21:00","2026-07-24T22:00","2026-07-24T23:00"],"wind_speed_10m":[11.1,9.2,7.7,7.8,7.1,9.3,10.5,11.7,13,15.7,13.5,8.7,6.6,5.1,4.9,5.6,7.9,5.5,3.6,4.7,5.2,4.8,4.4,4.1],"wind_direction_10m":[182,184,205,222,191,180,178,161,152,165,196,230,256,272,272,306,310,312,264,200,43,58,67,65]}},{"marine":{"time":["2026-07-24T00:00","2026-07-24T01:00","2026-07-24T02:00","2026-07-24T03:00","2026-07-24T04:00","2026-07-24T05:00","2026-07-24T06:00","2026-07-24T07:00","2026-07-24T08:00","2026-07-24T09:00","2026-07-24T10:00","2026-07-24T11:00","2026-07-24T12:00","2026-07-24T13:00","2026-07-24T14:00","2026-07-24T15:00","2026-07-24T16:00","2026-07-24T17:00","2026-07-24T18:00","2026-07-24T19:00","2026-07-24T20:00","2026-07-24T21:00","2026-07-24T22:00","2026-07-24T23:00"],"wave_height":[0.6,0.6,0.62,0.6,0.6,0.58,0.6,0.64,0.66,0.68,0.68,0.7,0.68,0.68,0.66,0.66,0.66,0.66,0.66,0.68,0.68,0.66,0.66,0.64],"wave_period":[4.05,4.1,4.15,4.25,4.35,4.4,4.35,4.2,4.15,4.15,4.25,4.3,4.35,4.45,4.5,4.5,4.5,4.45,4.45,4.4,4.4,4.45,4.5,4.55],"wave_direction":[60,62,64,65,67,68,67,65,64,64,64,64,64,63,63,63,62,62,62,62,62,63,63,64],"swell_wave_height":[0.28,0.3,0.34,0.34,0.34,0.34,0.34,0.34,0.34,0.34,0.34,0.34,0.34,0.36,0.36,0.34,0.34,0.32,0.32,0.32,0.32,0.34,0.34,0.36],"swell_wave_period":[4.05,4.6,5.1,5.4,5.55,5.65,5.7,5.7,5.7,5.75,5.8,5.8,5.6,5.3,5.1,5.05,5.15,5.2,5.25,5.3,5.3,5.2,5.05,4.9],"swell_wave_direction":[43,82,120,119,119,118,122,126,130,124,119,113,88,62,37,39,41,43,43,44,44,45,45,46]},"wind":{"time":["2026-07-24T00:00","2026-07-24T01:00","2026-07-24T02:00","2026-07-24T03:00","2026-07-24T04:00","2026-07-24T05:00","2026-07-24T06:00","2026-07-24T07:00","2026-07-24T08:00","2026-07-24T09:00","2026-07-24T10:00","2026-07-24T11:00","2026-07-24T12:00","2026-07-24T13:00","2026-07-24T14:00","2026-07-24T15:00","2026-07-24T16:00","2026-07-24T17:00","2026-07-24T18:00","2026-07-24T19:00","2026-07-24T20:00","2026-07-24T21:00","2026-07-24T22:00","2026-07-24T23:00"],"wind_speed_10m":[13.7,10.5,11.4,9.9,7.6,15.6,13.8,15.3,18.4,18.9,15.4,11.2,8.2,8,6.6,4.5,7,3.1,5.5,6.2,9.1,9.9,8.8,7.7],"wind_direction_10m":[188,183,217,230,203,179,177,158,151,156,162,233,236,236,284,270,312,300,259,204,132,58,65,65]}},{"marine":{"time":["2026-07-24T00:00","2026-07-24T01:00","2026-07-24T02:00","2026-07-24T03:00","2026-07-24T04:00","2026-07-24T05:00","2026-07-24T06:00","2026-07-24T07:00","2026-07-24T08:00","2026-07-24T09:00","2026-07-24T10:00","2026-07-24T11:00","2026-07-24T12:00","2026-07-24T13:00","2026-07-24T14:00","2026-07-24T15:00","2026-07-24T16:00","2026-07-24T17:00","2026-07-24T18:00","2026-07-24T19:00","2026-07-24T20:00","2026-07-24T21:00","2026-07-24T22:00","2026-07-24T23:00"],"wave_height":[0.66,0.66,0.66,0.66,0.66,0.66,0.68,0.7,0.72,0.72,0.74,0.74,0.74,0.72,0.72,0.72,0.72,0.72,0.72,0.72,0.72,0.7,0.7,0.68],"wave_period":[4.6,4.65,4.7,4.85,5,5.05,4.95,4.75,4.65,4.65,4.75,4.8,4.85,4.9,4.95,4.95,4.9,4.9,4.9,4.9,4.9,4.95,5,5.05],"wave_direction":[84,84,83,85,86,88,84,79,75,75,75,75,75,74,74,73,73,72,72,71,71,72,72,73],"swell_wave_height":[0.38,0.36,0.36,0.38,0.38,0.4,0.4,0.42,0.42,0.42,0.44,0.44,0.44,0.44,0.44,0.44,0.42,0.42,0.42,0.42,0.42,0.42,0.42,0.42],"swell_wave_period":[4.3,5.2,5.9,6.3,6.55,6.65,6.6,6.45,6.3,6.25,6.2,6.15,6.15,6.15,6.15,6.1,6.05,6.05,6.1,6.15,6.2,6.2,6.2,6.2],"swell_wave_direction":[145,138,131,130,130,129,129,130,130,131,131,132,131,130,129,129,128,128,128,128,128,128,128,128]},"wind":{"time":["2026-07-24T00:00","2026-07-24T01:00","2026-07-24T02:00","2026-07-24T03:00","2026-07-24T04:00","2026-07-24T05:00","2026-07-24T06:00","2026-07-24T07:00","2026-07-24T08:00","2026-07-24T09:00","2026-07-24T10:00","2026-07-24T11:00","2026-07-24T12:00","2026-07-24T13:00","2026-07-24T14:00","2026-07-24T15:00","2026-07-24T16:00","2026-07-24T17:00","2026-07-24T18:00","2026-07-24T19:00","2026-07-24T20:00","2026-07-24T21:00","2026-07-24T22:00","2026-07-24T23:00"],"wind_speed_10m":[16,8.1,10.5,6.4,8.3,11.3,14.4,12.4,18.6,19.2,16.1,16.8,14.7,11.1,11.4,8.6,6.3,7.7,5.2,5.9,7.3,8.2,7.9,6],"wind_direction_10m":[186,195,210,215,143,168,171,166,160,157,179,228,219,219,240,265,252,311,269,201,131,59,70,77]}},{"marine":{"time":["2026-07-24T00:00","2026-07-24T01:00","2026-07-24T02:00","2026-07-24T03:00","2026-07-24T04:00","2026-07-24T05:00","2026-07-24T06:00","2026-07-24T07:00","2026-07-24T08:00","2026-07-24T09:00","2026-07-24T10:00","2026-07-24T11:00","2026-07-24T12:00","2026-07-24T13:00","2026-07-24T14:00","2026-07-24T15:00","2026-07-24T16:00","2026-07-24T17:00","2026-07-24T18:00","2026-07-24T19:00","2026-07-24T20:00","2026-07-24T21:00","2026-07-24T22:00","2026-07-24T23:00"],"wave_height":[0.68,0.7,0.72,0.7,0.7,0.68,0.7,0.74,0.76,0.76,0.78,0.78,0.76,0.74,0.72,0.74,0.76,0.78,0.78,0.78,0.78,0.76,0.72,0.7],"wave_period":[4.9,4.8,4.8,4.95,5.15,5.25,5.2,5,4.9,4.85,4.85,4.9,5.1,5.35,5.5,5.4,5.2,5.05,5,4.95,5,5.1,5.25,5.4],"wave_direction":[121,110,100,102,105,107,100,94,87,86,84,83,86,88,91,86,82,77,76,76,75,78,81,84],"swell_wave_height":[0.46,0.42,0.4,0.4,0.4,0.4,0.4,0.42,0.42,0.44,0.48,0.5,0.5,0.52,0.52,0.52,0.52,0.52,0.5,0.5,0.48,0.48,0.48,0.48],"swell_wave_period":[3.35,3.2,3.5,4.6,6.05,7.1,7.3,7.1,6.8,6.5,6.2,5.95,5.9,6,6.05,6.05,6.05,6,5.95,5.9,5.85,5.85,5.85,5.85],"swell_wave_direction":[168,167,167,154,140,127,127,127,127,130,132,135,134,134,133,132,132,131,131,131,131,131,131,131]},"wind":{"time":["2026-07-24T00:00","2026-07-24T01:00","2026-07-24T02:00","2026-07-24T03:00","2026-07-24T04:00","2026-07-24T05:00","2026-07-24T06:00","2026-07-24T07:00","2026-07-24T08:00","2026-07-24T09:00","2026-07-24T10:00","2026-07-24T11:00","2026-07-24T12:00","2026-07-24T13:00","2026-07-24T14:00","2026-07-24T15:00","2026-07-24T16:00","2026-07-24T17:00","2026-07-24T18:00","2026-07-24T19:00","2026-07-24T20:00","2026-07-24T21:00","2026-07-24T22:00","2026-07-24T23:00"],"wind_speed_10m":[16.1,6.3,8.1,9.1,17.6,15.1,12.4,16.5,18.8,19.4,18.5,18.1,19.3,14.1,16.2,19,16,10.1,7.5,3,3.5,4,4.2,2.5],"wind_direction_10m":[195,187,191,157,175,168,166,155,164,162,177,216,195,195,224,203,221,242,289,202,122,55,77,113]}},{"marine":{"time":["2026-07-24T00:00","2026-07-24T01:00","2026-07-24T02:00","2026-07-24T03:00","2026-07-24T04:00","2026-07-24T05:00","2026-07-24T06:00","2026-07-24T07:00","2026-07-24T08:00","2026-07-24T09:00","2026-07-24T10:00","2026-07-24T11:00","2026-07-24T12:00","2026-07-24T13:00","2026-07-24T14:00","2026-07-24T15:00","2026-07-24T16:00","2026-07-24T17:00","2026-07-24T18:00","2026-07-24T19:00","2026-07-24T20:00","2026-07-24T21:00","2026-07-24T22:00","2026-07-24T23:00"],"wave_height":[0.74,0.74,0.74,0.76,0.76,0.78,0.78,0.8,0.8,0.8,0.82,0.82,0.8,0.78,0.76,0.78,0.78,0.8,0.8,0.78,0.78,0.76,0.74,0.72],"wave_period":[5.5,5.5,5.5,5.45,5.45,5.4,5.4,5.45,5.45,5.4,5.4,5.4,5.55,5.75,5.85,5.8,5.6,5.5,5.5,5.5,5.55,5.65,5.75,5.8],"wave_direction":[158,153,149,143,137,131,128,125,122,117,111,106,109,111,114,111,107,104,103,102,101,103,104,106],"swell_wave_height":[0.58,0.56,0.52,0.5,0.5,0.48,0.48,0.48,0.48,0.5,0.5,0.52,0.54,0.56,0.58,0.58,0.58,0.58,0.58,0.58,0.58,0.58,0.56,0.56],"swell_wave_period":[3.45,3.25,3.45,4.3,5.45,6.4,6.8,7,7.05,7.05,6.95,6.8,6.55,6.3,6.05,5.95,5.85,5.8,5.7,5.65,5.6,5.6,5.55,5.55],"swell_wave_direction":[178,177,177,163,150,136,134,131,129,129,130,130,131,133,134,134,134,134,135,137,138,138,138,138]},"wind":{"time":["2026-07-24T00:00","2026-07-24T01:00","2026-07-24T02:00","2026-07-24T03:00","2026-07-24T04:00","2026-07-24T05:00","2026-07-24T06:00","2026-07-24T07:00","2026-07-24T08:00","2026-07-24T09:00","2026-07-24T10:00","2026-07-24T11:00","2026-07-24T12:00","2026-07-24T13:00","2026-07-24T14:00","2026-07-24T15:00","2026-07-24T16:00","2026-07-24T17:00","2026-07-24T18:00","2026-07-24T19:00","2026-07-24T20:00","2026-07-24T21:00","2026-07-24T22:00","2026-07-24T23:00"],"wind_speed_10m":[6.5,2.8,4.2,6.1,8.3,24.8,15.1,18.5,15.5,13.8,17.1,16,20.4,16.2,19.9,17,15.2,11.2,8.5,6.9,5.1,5.1,6.9,6.8],"wind_direction_10m":[279,286,124,158,141,185,172,152,146,181,188,207,227,228,205,198,215,233,231,246,243,230,212,187]}},{"marine":{"time":["2026-07-24T00:00","2026-07-24T01:00","2026-07-24T02:00","2026-07-24T03:00","2026-07-24T04:00","2026-07-24T05:00","2026-07-24T06:00","2026-07-24T07:00","2026-07-24T08:00","2026-07-24T09:00","2026-07-24T10:00","2026-07-24T11:00","2026-07-24T12:00","2026-07-24T13:00","2026-07-24T14:00","2026-07-24T15:00","2026-07-24T16:00","2026-07-24T17:00","2026-07-24T18:00","2026-07-24T19:00","2026-07-24T20:00","2026-07-24T21:00","2026-07-24T22:00","2026-07-24T23:00"],"wave_height":[1,0.98,0.98,0.98,0.98,0.98,0.98,0.98,0.98,0.98,1,1,0.98,0.98,0.96,0.94,0.94,0.92,0.92,0.92,0.92,0.92,0.9,0.9],"wave_period":[5.9,6,6.05,6.1,6.15,6.15,6.15,6.15,6.15,6.1,6.05,6.05,6.1,6.2,6.3,6.35,6.4,6.4,6.4,6.35,6.35,6.35,6.4,6.4],"wave_direction":[164,160,157,154,151,148,145,141,138,133,128,123,123,123,123,123,124,124,122,119,117,117,118,118],"swell_wave_height":[0.8,0.76,0.72,0.7,0.68,0.66,0.68,0.68,0.7,0.7,0.72,0.72,0.74,0.76,0.78,0.78,0.78,0.78,0.78,0.8,0.8,0.8,0.78,0.78],"swell_wave_period":[3.55,3.4,3.6,4.65,6.1,7.15,7.4,7.25,7.05,7,6.9,6.75,6.55,6.35,6.15,6.05,5.95,5.9,5.8,5.7,5.65,5.65,5.7,5.7],"swell_wave_direction":[182,182,181,164,148,131,131,131,131,131,132,132,132,133,133,133,134,134,136,137,139,139,138,138]},"wind":{"time":["2026-07-24T00:00","2026-07-24T01:00","2026-07-24T02:00","2026-07-24T03:00","2026-07-24T04:00","2026-07-24T05:00","2026-07-24T06:00","2026-07-24T07:00","2026-07-24T08:00","2026-07-24T09:00","2026-07-24T10:00","2026-07-24T11:00","2026-07-24T12:00","2026-07-24T13:00","2026-07-24T14:00","2026-07-24T15:00","2026-07-24T16:00","2026-07-24T17:00","2026-07-24T18:00","2026-07-24T19:00","2026-07-24T20:00","2026-07-24T21:00","2026-07-24T22:00","2026-07-24T23:00"],"wind_speed_10m":[8.9,4.8,2.2,2,3.8,7.8,9.5,20.1,14.4,12.8,18.6,18.3,21.5,16.2,17.5,17.4,14.5,11.1,8.7,7.8,7.4,6.9,8,6.4],"wind_direction_10m":[286,243,165,17,168,267,180,142,151,172,187,201,254,241,226,194,208,223,235,233,232,212,194,157]}},{"marine":{"time":["2026-07-24T00:00","2026-07-24T01:00","2026-07-24T02:00","2026-07-24T03:00","2026-07-24T04:00","2026-07-24T05:00","2026-07-24T06:00","2026-07-24T07:00","2026-07-24T08:00","2026-07-24T09:00","2026-07-24T10:00","2026-07-24T11:00","2026-07-24T12:00","2026-07-24T13:00","2026-07-24T14:00","2026-07-24T15:00","2026-07-24T16:00","2026-07-24T17:00","2026-07-24T18:00","2026-07-24T19:00","2026-07-24T20:00","2026-07-24T21:00","2026-07-24T22:00","2026-07-24T23:00"],"wave_height":[0.9,0.9,0.88,0.88,0.9,0.9,0.9,0.88,0.88,0.88,0.9,0.9,0.9,0.88,0.88,0.86,0.86,0.84,0.84,0.82,0.82,0.82,0.8,0.8],"wave_period":[5.8,5.9,5.95,6,6,6,6,6.05,6.05,6,5.9,5.9,6,6.1,6.2,6.25,6.25,6.25,6.25,6.25,6.25,6.25,6.3,6.3],"wave_direction":[166,163,160,156,151,147,145,143,141,135,130,124,125,127,128,127,127,126,125,124,123,125,126,128],"swell_wave_height":[0.76,0.72,0.68,0.66,0.64,0.62,0.62,0.62,0.62,0.64,0.64,0.66,0.68,0.68,0.7,0.7,0.7,0.7,0.7,0.7,0.7,0.7,0.7,0.7],"swell_wave_period":[3.7,3.65,3.65,3.7,3.85,4.25,5.1,6.2,6.95,7.05,6.75,6.5,6.35,6.25,6.15,6.05,6,5.95,5.9,5.8,5.75,5.7,5.7,5.65],"swell_wave_direction":[182,182,181,180,179,178,163,148,133,133,134,134,134,134,134,134,134,134,135,136,137,137,137,137]},"wind":{"time":["2026-07-24T00:00","2026-07-24T01:00","2026-07-24T02:00","2026-07-24T03:00","2026-07-24T04:00","2026-07-24T05:00","2026-07-24T06:00","2026-07-24T07:00","2026-07-24T08:00","2026-07-24T09:00","2026-07-24T10:00","2026-07-24T11:00","2026-07-24T12:00","2026-07-24T13:00","2026-07-24T14:00","2026-07-24T15:00","2026-07-24T16:00","2026-07-24T17:00","2026-07-24T18:00","2026-07-24T19:00","2026-07-24T20:00","2026-07-24T21:00","2026-07-24T22:00","2026-07-24T23:00"],"wind_speed_10m":[11.2,9.4,11.5,9.2,21.3,3.8,11.7,18.5,19.9,16.3,19.8,22,16.5,12.3,19.2,12.3,10.5,10,9.2,8.6,6.9,7.1,7.4,5.9],"wind_direction_10m":[240,218,164,205,232,165,156,146,185,177,208,191,271,249,226,178,211,223,231,238,225,209,182,157]}},{"marine":{"time":["2026-07-24T00:00","2026-07-24T01:00","2026-07-24T02:00","2026-07-24T03:00","2026-07-24T04:00","2026-07-24T05:00","2026-07-24T06:00","2026-07-24T07:00","2026-07-24T08:00","2026-07-24T09:00","2026-07-24T10:00","2026-07-24T11:00","2026-07-24T12:00","2026-07-24T13:00","2026-07-24T14:00","2026-07-24T15:00","2026-07-24T16:00","2026-07-24T17:00","2026-07-24T18:00","2026-07-24T19:00","2026-07-24T20:00","2026-07-24T21:00","2026-07-24T22:00","2026-07-24T23:00"],"wave_height":[0.98,0.96,0.96,0.96,0.96,0.96,0.96,0.94,0.94,0.94,0.96,0.96,0.96,0.94,0.94,0.92,0.92,0.9,0.9,0.88,0.88,0.88,0.88,0.88],"wave_period":[5.9,6,6.1,6.15,6.15,6.15,6.15,6.2,6.2,6.2,6.15,6.15,6.2,6.25,6.3,6.35,6.45,6.5,6.5,6.5,6.45,6.4,6.4,6.35],"wave_direction":[167,164,161,158,154,151,148,144,141,137,134,130,130,129,129,130,132,133,131,130,128,129,130,131],"swell_wave_height":[0.8,0.78,0.74,0.72,0.68,0.66,0.68,0.7,0.72,0.72,0.72,0.72,0.74,0.74,0.76,0.76,0.76,0.76,0.76,0.74,0.74,0.74,0.76,0.76],"swell_wave_period":[3.7,3.6,3.7,4.2,4.9,5.55,6.05,6.45,6.7,6.7,6.5,6.35,6.25,6.2,6.15,6.1,6.05,6,6,5.95,5.95,5.9,5.85,5.8],"swell_wave_direction":[185,185,184,171,158,145,140,136,131,131,132,132,132,133,133,133,133,133,133,132,132,132,133,133]},"wind":{"time":["2026-07-24T00:00","2026-07-24T01:00","2026-07-24T02:00","2026-07-24T03:00","2026-07-24T04:00","2026-07-24T05:00","2026-07-24T06:00","2026-07-24T07:00","2026-07-24T08:00","2026-07-24T09:00","2026-07-24T10:00","2026-07-24T11:00","2026-07-24T12:00","2026-07-24T13:00","2026-07-24T14:00","2026-07-24T15:00","2026-07-24T16:00","2026-07-24T17:00","2026-07-24T18:00","2026-07-24T19:00","2026-07-24T20:00","2026-07-24T21:00","2026-07-24T22:00","2026-07-24T23:00"],"wind_speed_10m":[12.7,10,7.6,16.9,21.9,8.7,10.8,24.9,19.1,17.2,18.4,23.2,32.8,15.8,12.7,11.3,9,10,10.2,8.6,7.6,7.8,6.8,5.7],"wind_direction_10m":[241,212,181,189,218,190,172,173,189,196,203,206,246,228,187,178,210,237,236,234,218,207,177,164]}},{"marine":{"time":["2026-07-24T00:00","2026-07-24T01:00","2026-07-24T02:00","2026-07-24T03:00","2026-07-24T04:00","2026-07-24T05:00","2026-07-24T06:00","2026-07-24T07:00","2026-07-24T08:00","2026-07-24T09:00","2026-07-24T10:00","2026-07-24T11:00","2026-07-24T12:00","2026-07-24T13:00","2026-07-24T14:00","2026-07-24T15:00","2026-07-24T16:00","2026-07-24T17:00","2026-07-24T18:00","2026-07-24T19:00","2026-07-24T20:00","2026-07-24T21:00","2026-07-24T22:00","2026-07-24T23:00"],"wave_height":[0.9,0.9,0.88,0.88,0.9,0.9,0.9,0.9,0.9,0.9,0.9,0.9,0.9,0.9,0.9,0.88,0.88,0.86,0.86,0.84,0.84,0.84,0.82,0.82],"wave_period":[5.9,6.05,6.1,6.1,6.05,6.05,6.1,6.15,6.2,6.2,6.2,6.2,6.2,6.25,6.3,6.35,6.45,6.5,6.5,6.45,6.45,6.45,6.45,6.45],"wave_direction":[166,162,159,156,153,150,147,143,140,138,135,133,132,131,130,131,133,134,133,132,131,130,130,129],"swell_wave_height":[0.74,0.7,0.66,0.64,0.64,0.62,0.64,0.64,0.66,0.68,0.68,0.7,0.7,0.72,0.72,0.72,0.72,0.72,0.72,0.72,0.72,0.72,0.72,0.72],"swell_wave_period":[3.6,3.5,3.7,4.45,5.55,6.35,6.7,6.75,6.75,6.65,6.5,6.35,6.3,6.3,6.25,6.15,6.1,6,5.95,5.9,5.85,5.85,5.85,5.85],"swell_wave_direction":[184,183,182,169,155,142,138,135,131,131,132,132,132,131,131,131,132,132,132,133,133,133,133,133]},"wind":{"time":["2026-07-24T00:00","2026-07-24T01:00","2026-07-24T02:00","2026-07-24T03:00","2026-07-24T04:00","2026-07-24T05:00","2026-07-24T06:00","2026-07-24T07:00","2026-07-24T08:00","2026-07-24T09:00","2026-07-24T10:00","2026-07-24T11:00","2026-07-24T12:00","2026-07-24T13:00","2026-07-24T14:00","2026-07-24T15:00","2026-07-24T16:00","2026-07-24T17:00","2026-07-24T18:00","2026-07-24T19:00","2026-07-24T20:00","2026-07-24T21:00","2026-07-24T22:00","2026-07-24T23:00"],"wind_speed_10m":[9.2,7.1,11.5,18.1,10.3,12.8,11.6,17.9,16.9,15.5,15.8,20,14.4,6.5,3,5.2,6.2,7.5,7.6,6.1,5.9,5.5,6.4,6.4],"wind_direction_10m":[205,206,176,235,165,181,188,179,193,195,219,251,259,207,203,222,219,242,220,212,201,162,168,180]}}]},"buoys_forecast":{"41001":{"lat":34.791,"lon":-72.42,"marine":{"time":["2026-07-24T00:00","2026-07-24T01:00","2026-07-24T02:00","2026-07-24T03:00","2026-07-24T04:00","2026-07-24T05:00","2026-07-24T06:00","2026-07-24T07:00","2026-07-24T08:00","2026-07-24T09:00","2026-07-24T10:00","2026-07-24T11:00","2026-07-24T12:00","2026-07-24T13:00","2026-07-24T14:00","2026-07-24T15:00","2026-07-24T16:00","2026-07-24T17:00","2026-07-24T18:00","2026-07-24T19:00","2026-07-24T20:00","2026-07-24T21:00","2026-07-24T22:00","2026-07-24T23:00"],"wave_height":[1.54,1.52,1.5,1.48,1.44,1.42,1.4,1.36,1.34,1.32,1.28,1.26,1.24,1.24,1.22,1.2,1.2,1.18,1.18,1.16,1.16,1.16,1.14,1.14],"wave_period":[6.35,6.3,6.3,6.3,6.25,6.25,6.25,6.2,6.2,6.2,6.15,6.15,6.15,6.1,6.1,6.1,6.1,6.15,6.2,6.25,6.3,6.35,6.4,6.4],"wave_direction":[210,207,205,203,202,200,199,197,196,195,193,192,189,185,182,177,173,168,164,160,156,153,150,147],"swell_wave_height":[1.1,1.06,1.04,1.02,1,0.98,0.96,0.96,0.94,0.92,0.9,0.88,0.88,0.88,0.88,0.88,0.9,0.9,0.9,0.92,0.92,0.92,0.94,0.94],"swell_wave_period":[4.95,4.9,4.85,4.9,4.95,5,4.95,4.8,4.8,4.95,5.15,5.35,5.5,5.6,5.7,5.7,5.6,5.6,5.7,5.85,5.95,6,6,6],"swell_wave_direction":[264,262,261,252,244,235,235,235,235,236,237,238,204,171,137,137,137,137,137,137,137,137,137,137]},"wind":{"time":["2026-07-24T00:00","2026-07-24T01:00","2026-07-24T02:00","2026-07-24T03:00","2026-07-24T04:00","2026-07-24T05:00","2026-07-24T06:00","2026-07-24T07:00","2026-07-24T08:00","2026-07-24T09:00","2026-07-24T10:00","2026-07-24T11:00","2026-07-24T12:00","2026-07-24T13:00","2026-07-24T14:00","2026-07-24T15:00","2026-07-24T16:00","2026-07-24T17:00","2026-07-24T18:00","2026-07-24T19:00","2026-07-24T20:00","2026-07-24T21:00","2026-07-24T22:00","2026-07-24T23:00"],"wind_speed_10m":[12.5,12.7,11.6,12.5,13.4,12.9,14.6,15.5,14.1,15.8,14.2,12.9,13.1,13.8,13.2,12,12.1,10.9,10.6,9.3,5.7,3.8,7.2,7.4],"wind_direction_10m":[149,153,162,168,167,165,169,172,174,175,189,185,174,190,188,189,175,182,210,165,166,150,166,182]}},"41002":{"lat":31.743,"lon":-74.955,"marine":{"time":["2026-07-24T00:00","2026-07-24T01:00","2026-07-24T02:00","2026-07-24T03:00","2026-07-24T04:00","2026-07-24T05:00","2026-07-24T06:00","2026-07-24T07:00","2026-07-24T08:00","2026-07-24T09:00","2026-07-24T10:00","2026-07-24T11:00","2026-07-24T12:00","2026-07-24T13:00","2026-07-24T14:00","2026-07-24T15:00","2026-07-24T16:00","2026-07-24T17:00","2026-07-24T18:00","2026-07-24T19:00","2026-07-24T20:00","2026-07-24T21:00","2026-07-24T22:00","2026-07-24T23:00"],"wave_height":[1.3,1.28,1.28,1.28,1.26,1.26,1.26,1.24,1.24,1.22,1.22,1.2,1.2,1.18,1.18,1.18,1.16,1.16,1.16,1.14,1.14,1.14,1.14,1.14],"wave_period":[7.25,7.2,7.2,7.15,7.15,7.1,7.1,7.1,7.1,7.1,7.05,7.05,7,7,6.95,6.95,6.95,6.95,6.95,7,7,7,6.95,6.95],"wave_direction":[122,122,121,121,121,121,121,121,121,121,121,121,121,120,120,120,119,119,119,118,118,118,117,117],"swell_wave_height":[1.26,1.26,1.26,1.26,1.24,1.24,1.22,1.22,1.2,1.2,1.18,1.18,1.18,1.16,1.16,1.16,1.14,1.14,1.14,1.14,1.14,1.14,1.12,1.12],"swell_wave_period":[6.2,6.2,6.2,6.15,6.15,6.1,6.05,6.05,6,6,6,6,5.95,5.9,5.85,5.85,5.9,5.9,5.9,5.9,5.9,5.9,5.9,5.9],"swell_wave_direction":[120,120,119,119,119,119,119,120,120,120,120,120,120,119,119,119,118,118,118,117,117,117,116,116]},"wind":{"time":["2026-07-24T00:00","2026-07-24T01:00","2026-07-24T02:00","2026-07-24T03:00","2026-07-24T04:00","2026-07-24T05:00","2026-07-24T06:00","2026-07-24T07:00","2026-07-24T08:00","2026-07-24T09:00","2026-07-24T10:00","2026-07-24T11:00","2026-07-24T12:00","2026-07-24T13:00","2026-07-24T14:00","2026-07-24T15:00","2026-07-24T16:00","2026-07-24T17:00","2026-07-24T18:00","2026-07-24T19:00","2026-07-24T20:00","2026-07-24T21:00","2026-07-24T22:00","2026-07-24T23:00"],"wind_speed_10m":[10.3,10.6,10.8,13.7,13.1,16.2,13.9,12.8,10.7,11.7,9.8,7.5,8.7,8.6,9,6.4,4.6,6.7,7.2,6.4,5.7,6.2,7.3,7.9],"wind_direction_10m":[136,126,129,141,153,147,155,167,182,169,153,165,160,166,167,177,152,147,145,151,157,156,148,160]}},"41025":{"lat":35.026,"lon":-75.38,"marine":{"time":["2026-07-24T00:00","2026-07-24T01:00","2026-07-24T02:00","2026-07-24T03:00","2026-07-24T04:00","2026-07-24T05:00","2026-07-24T06:00","2026-07-24T07:00","2026-07-24T08:00","2026-07-24T09:00","2026-07-24T10:00","2026-07-24T11:00","2026-07-24T12:00","2026-07-24T13:00","2026-07-24T14:00","2026-07-24T15:00","2026-07-24T16:00","2026-07-24T17:00","2026-07-24T18:00","2026-07-24T19:00","2026-07-24T20:00","2026-07-24T21:00","2026-07-24T22:00","2026-07-24T23:00"],"wave_height":[1.06,1.04,1.04,1.04,1.04,1.04,1.04,1.04,1.04,1.04,1.06,1.06,1.06,1.06,1.06,1.04,1.04,1.02,1.02,1,1,1,1,1],"wave_period":[6,6.05,6.15,6.2,6.3,6.35,6.4,6.45,6.5,6.5,6.45,6.45,6.45,6.5,6.5,6.55,6.55,6.6,6.65,6.7,6.7,6.7,6.7,6.65],"wave_direction":[164,162,159,156,153,150,147,145,142,138,134,130,128,125,123,123,122,122,121,120,119,118,117,116],"swell_wave_height":[0.78,0.74,0.72,0.74,0.76,0.78,0.8,0.82,0.84,0.84,0.86,0.86,0.86,0.86,0.86,0.86,0.86,0.86,0.86,0.84,0.84,0.84,0.84,0.84],"swell_wave_period":[4.9,6,6.8,7.05,7.05,7,6.95,6.9,6.8,6.75,6.65,6.6,6.55,6.5,6.45,6.4,6.35,6.3,6.3,6.25,6.25,6.25,6.2,6.2],"swell_wave_direction":[163,147,130,130,131,131,131,132,132,132,131,131,131,131,131,131,131,131,131,131,131,131,132,132]},"wind":{"time":["2026-07-24T00:00","2026-07-24T01:00","2026-07-24T02:00","2026-07-24T03:00","2026-07-24T04:00","2026-07-24T05:00","2026-07-24T06:00","2026-07-24T07:00","2026-07-24T08:00","2026-07-24T09:00","2026-07-24T10:00","2026-07-24T11:00","2026-07-24T12:00","2026-07-24T13:00","2026-07-24T14:00","2026-07-24T15:00","2026-07-24T16:00","2026-07-24T17:00","2026-07-24T18:00","2026-07-24T19:00","2026-07-24T20:00","2026-07-24T21:00","2026-07-24T22:00","2026-07-24T23:00"],"wind_speed_10m":[17.3,5.9,12.8,6.4,13.4,10.3,11.2,3.4,19.9,14.9,16.3,17.9,16.6,14.2,7.7,15.4,10.5,10.6,13.3,10.1,7.4,7,5.1,7],"wind_direction_10m":[201,203,194,183,197,238,160,31,197,187,168,209,223,268,246,244,185,234,226,226,210,186,173,166]}},"44100":{"lat":36.257,"lon":-75.593,"marine":{"time":["2026-07-24T00:00","2026-07-24T01:00","2026-07-24T02:00","2026-07-24T03:00","2026-07-24T04:00","2026-07-24T05:00","2026-07-24T06:00","2026-07-24T07:00","2026-07-24T08:00","2026-07-24T09:00","2026-07-24T10:00","2026-07-24T11:00","2026-07-24T12:00","2026-07-24T13:00","2026-07-24T14:00","2026-07-24T15:00","2026-07-24T16:00","2026-07-24T17:00","2026-07-24T18:00","2026-07-24T19:00","2026-07-24T20:00","2026-07-24T21:00","2026-07-24T22:00","2026-07-24T23:00"],"wave_height":[0.82,0.8,0.8,0.8,0.82,0.82,0.84,0.84,0.86,0.88,0.88,0.9,0.9,0.9,0.9,0.9,0.92,0.92,0.92,0.9,0.9,0.88,0.88,0.86],"wave_period":[4.7,4.75,4.8,4.85,4.9,4.9,4.9,4.85,4.8,4.8,4.8,4.8,4.85,4.9,4.95,4.95,4.95,4.95,4.95,4.95,5,5.05,5.15,5.2],"wave_direction":[75,76,77,78,78,79,77,76,74,73,72,71,72,72,73,73,73,73,73,74,74,75,75,76],"swell_wave_height":[0.4,0.4,0.38,0.38,0.4,0.4,0.42,0.46,0.48,0.48,0.48,0.48,0.48,0.48,0.48,0.48,0.48,0.48,0.48,0.48,0.48,0.54,0.58,0.64],"swell_wave_period":[3.45,3.4,3.75,4.8,6.2,7.15,7.15,6.65,6.25,6.35,6.55,6.45,5.75,4.8,4.15,4.1,4.35,4.5,4.5,4.4,4.3,4.1,3.85,3.75],"swell_wave_direction":[20,23,25,57,89,121,123,125,127,127,127,127,94,60,27,42,56,71,64,58,51,53,54,56]},"wind":{"time":["2026-07-24T00:00","2026-07-24T01:00","2026-07-24T02:00","2026-07-24T03:00","2026-07-24T04:00","2026-07-24T05:00","2026-07-24T06:00","2026-07-24T07:00","2026-07-24T08:00","2026-07-24T09:00","2026-07-24T10:00","2026-07-24T11:00","2026-07-24T12:00","2026-07-24T13:00","2026-07-24T14:00","2026-07-24T15:00","2026-07-24T16:00","2026-07-24T17:00","2026-07-24T18:00","2026-07-24T19:00","2026-07-24T20:00","2026-07-24T21:00","2026-07-24T22:00","2026-07-24T23:00"],"wind_speed_10m":[3.4,9.8,10.1,12,12.3,10.1,11.9,10.2,17.8,28.4,23.4,12.4,15.9,15.4,14.2,12.9,11.9,14,12.1,11.5,10.3,9.7,9.3,8.6],"wind_direction_10m":[254,221,212,209,207,216,201,159,143,154,194,286,316,315,318,308,322,333,267,202,128,60,61,65]}}}}